MANIFEST.in
README.md
package_info.json
requirements.txt
setup.py
th2_data_services/data_source/rdp/__init__.py
th2_data_services/data_source/rdp/commands/__init__.py
th2_data_services/data_source/rdp/commands/http.py
th2_data_services/data_source/rdp/data_source/__init__.py
th2_data_services/data_source/rdp/data_source/http.py
th2_data_services/data_source/rdp/source_api/__init__.py
th2_data_services/data_source/rdp/source_api/http.py
th2_data_services_rdp.egg-info/PKG-INFO
th2_data_services_rdp.egg-info/SOURCES.txt
th2_data_services_rdp.egg-info/dependency_links.txt
th2_data_services_rdp.egg-info/requires.txt
th2_data_services_rdp.egg-info/top_level.txt