Metadata-Version: 2.1
Name: th2-data-services-rdp
Version: 0.0.0.1.dev11486288321
Summary: th2_data_services_rdp
Home-page: https://github.com/th2-net/th2-ds-source-lwdp
Author: TH2-devs
Author-email: th2-devs@exactprosystems.com
License: Apache License 2.0
Platform: UNKNOWN
Requires-Python: >=3.8
